README.md
setup.py
flask_ext_ydf/__init__.py
flask_ext_ydf/flask_ext_ydf.py
flask_ext_ydf.egg-info/PKG-INFO
flask_ext_ydf.egg-info/SOURCES.txt
flask_ext_ydf.egg-info/dependency_links.txt
flask_ext_ydf.egg-info/requires.txt
flask_ext_ydf.egg-info/top_level.txt